The_best_quote/Binomialdistribution.py
The_best_quote/Gaussiandistribution.py
The_best_quote/Generaldistribution.py
The_best_quote/__init__.py
The_best_quote-0.0.8.dist-info/LICENSE
The_best_quote-0.0.8.dist-info/METADATA
The_best_quote-0.0.8.dist-info/WHEEL
The_best_quote-0.0.8.dist-info/top_level.txt
The_best_quote-0.0.8.dist-info/RECORD
