Metadata-Version: 2.1
Name: The-best-quote
Version: 0.0.8
Summary: This is the simplest module for quick work with files.
Home-page: https://github.com/Agagarkin/The_best_quote.git
Author: agagarkin
Author-email: eshkereholskill@gmail.com
Project-URL: GitHub, https://github.com/Agagarkin/The_best_quote.git
Keywords: files speedfiles
Classifier: Programming Language :: Python :: 3.11
Classifier: License :: OSI Approved :: MIT License
Classifier: Operating System :: OS Independent
Requires-Python: >=3.6
License-File: LICENSE
Requires-Dist: requests >=2.25.1
